metools/__init__.py
metools/time.py
metools/time.py.md
metools-0.0.2.dist-info/METADATA
metools-0.0.2.dist-info/WHEEL
metools-0.0.2.dist-info/entry_points.txt
metools-0.0.2.dist-info/RECORD
