Metadata-Version: 2.4
Name: metools
Version: 0.0.2
Summary: 常用小工具
Project-URL: Homepage, https://github.com/111hgx/metools
Author-email: haogaoxing <jjx000@qq.com>
License: MIT
Requires-Python: >=3.8
